reputationsystemstest/__init__.py
reputationsystemstest/poetry.lock
reputationsystemstest/simulations/__init__.py
reputationsystemstest/simulations/simulator_class.py
reputationsystemstest/tests/__init__.py
reputationsystemstest/tests/test_simulator_class.py
reputationsystemstest-0.0.1.dist-info/METADATA
reputationsystemstest-0.0.1.dist-info/WHEEL
reputationsystemstest-0.0.1.dist-info/RECORD
