Metadata-Version: 2.1
Name: reputationsystemstest
Version: 0.0.1
Summary: Dynamic Structural Modeling and Approximate Bayesian Inference of Online Reputation System
Author: Shrabastee Banerjee
Requires-Python: >=3.9.16,<4.0.0
Classifier: Programming Language :: Python :: 3
Classifier: Programming Language :: Python :: 3.10
Classifier: Programming Language :: Python :: 3.11
Requires-Dist: arviz (>=0.13.0,<0.14.0)
Requires-Dist: black (>=22.8.0,<23.0.0)
Requires-Dist: hyperopt (>=0.2.7,<0.3.0)
Requires-Dist: mlflow (>=2.0.1,<3.0.0)
Requires-Dist: mypy (>=1.0.0,<2.0.0)
Requires-Dist: pyreadr (>=0.4.6,<0.5.0)
Requires-Dist: sbi (>=0.20.0,<0.21.0)
Requires-Dist: torch (==1.12.0)
Requires-Dist: torchaudio (==0.12.0)
Requires-Dist: torchvision (==0.13.0)
Requires-Dist: tqdm (>=4.64.0,<5.0.0)
